safeloader/.gitattributes
safeloader/__init__.py
safeloader/safeloader.py
safeloader-0.1.2.dist-info/LICENSE.txt
safeloader-0.1.2.dist-info/METADATA
safeloader-0.1.2.dist-info/WHEEL
safeloader-0.1.2.dist-info/top_level.txt
safeloader-0.1.2.dist-info/RECORD
